hy2dl/__init__.py
hy2dl/datasetzoo/__init__.py
hy2dl/datasetzoo/basedataset.py
hy2dl/datasetzoo/camelsde.py
hy2dl/datasetzoo/camelsgb.py
hy2dl/datasetzoo/camelsus.py
hy2dl/datasetzoo/caravan.py
hy2dl/datasetzoo/hourlycamelsde.py
hy2dl/datasetzoo/hourlycamelsus.py
hy2dl/evaluation/__init__.py
hy2dl/evaluation/metrics.py
hy2dl/modelzoo/__init__.py
hy2dl/modelzoo/baseconceptualmodel.py
hy2dl/modelzoo/cudalstm.py
hy2dl/modelzoo/forecast_lstm.py
hy2dl/modelzoo/hbv.py
hy2dl/modelzoo/hybrid.py
hy2dl/modelzoo/inputlayer.py
hy2dl/modelzoo/linear_reservoir.py
hy2dl/modelzoo/lstmmdn.py
hy2dl/modelzoo/nonsense.py
hy2dl/modelzoo/shm.py
hy2dl/modelzoo/uh_routing.py
hy2dl/training/__init__.py
hy2dl/training/loss.py
hy2dl/utils/__init__.py
hy2dl/utils/config.py
hy2dl/utils/distributions.py
hy2dl/utils/logging.py
hy2dl/utils/optimizer.py
hy2dl/utils/utils.py
hy2dl-1.0.1.dist-info/WHEEL
hy2dl-1.0.1.dist-info/METADATA
hy2dl-1.0.1.dist-info/RECORD
