Metadata-Version: 2.3
Name: hy2dl
Version: 1.0.1
Summary: Python library to create hydrological models for rainfall-runoff prediction using deep learning methods
Author: Eduardo Acuña Espinoza, Manuel Álvarez Chaves
Author-email: Eduardo Acuña Espinoza <eduardo.espinoza@kit.edu>, Manuel Álvarez Chaves <manuel.alvarez-chaves@simtech.uni-stuttgart.de>
License: MIT License
Requires-Dist: numpy>=2.2.0
Requires-Dist: pandas>=2.2.0
Requires-Dist: pyyaml>=6.0.2
Requires-Dist: torch>=2.2.1
Requires-Dist: tqdm>=4.67.1
Requires-Dist: xarray[io]>=2025.6.1
Requires-Python: >=3.10
Project-URL: Documentation, https://hy2dl.readthedocs.io/
Project-URL: Repository, https://github.com/eduardoAcunaEspinoza/Hy2DL
